{"body": "{\"context\":{\"client\":{\"hl\":\"ru\",\"gl\":\"RU\",\"clientName\":1,\"clientVersion\":\"2.20200404.04.01\"}},\"events\":[{\"eventTimeMs\":1586269506309,\"latencyActionInfo\":{\"videoId\":\"8MfD-_YJL9U\",\"clientActionNonce\":\"FkNqj-KfJE3aiu7N\"},\"context\":{\"lastActivityMs\":\"157\"}},{\"eventTimeMs\":1586269506309,\"latencyActionInfo\":{\"clientPlaybackNonce\":\"lmRATwtI0wG9kD1g\",\"clientActionNonce\":\"FkNqj-KfJE3aiu7N\"},\"context\":{\"lastActivityMs\":\"157\"}},{\"eventTimeMs\":1586269506309,\"latencyActionInfo\":{\"playerInfo\":{\"itag\":\"243\"},\"clientActionNonce\":\"FkNqj-KfJE3aiu7N\"},\"context\":{\"lastActivityMs\":\"157\"}},{\"eventTimeMs\":1586269505730,\"latencyActionTicked\":{\"tickName\":\"gv\",\"clientActionNonce\":\"FkNqj-KfJE3aiu7N\"},\"context\":{\"lastActivityMs\":\"-1\"}},{\"eventTimeMs\":1586269506224,\"latencyActionTicked\":{\"tickName\":\"ada\",\"clientActionNonce\":\"FkNqj-KfJE3aiu7N\"},\"context\":{\"lastActivityMs\":\"-1\"}},{\"eventTimeMs\":1586269506234,\"latencyActionTicked\":{\"tickName\":\"vda\",\"clientActionNonce\":\"FkNqj-KfJE3aiu7N\"},\"context\":{\"lastActivityMs\":\"-1\"}},{\"eventTimeMs\":1586269505729,\"latencyActionTicked\":{\"tickName\":\"vri\",\"clientActionNonce\":\"FkNqj-KfJE3aiu7N\"},\"context\":{\"lastActivityMs\":\"-1\"}},{\"eventTimeMs\":1586269505729,\"latencyActionTicked\":{\"tickName\":\"vdns\",\"clientActionNonce\":\"FkNqj-KfJE3aiu7N\"},\"context\":{\"lastActivityMs\":\"-1\"}},{\"eventTimeMs\":1586269506183,\"latencyActionTicked\":{\"tickName\":\"vreq\",\"clientActionNonce\":\"FkNqj-KfJE3aiu7N\"},\"context\":{\"lastActivityMs\":\"-1\"}},{\"eventTimeMs\":1586269506207,\"latencyActionTicked\":{\"tickName\":\"fvb\",\"clientActionNonce\":\"FkNqj-KfJE3aiu7N\"},\"context\":{\"lastActivityMs\":\"-1\"}},{\"eventTimeMs\":1586269506232,\"latencyActionTicked\":{\"tickName\":\"vrc\",\"clientActionNonce\":\"FkNqj-KfJE3aiu7N\"},\"context\":{\"lastActivityMs\":\"-1\"}},{\"eventTimeMs\":1586269505729,\"latencyActionTicked\":{\"tickName\":\"ari\",\"clientActionNonce\":\"FkNqj-KfJE3aiu7N\"},\"context\":{\"lastActivityMs\":\"-1\"}},{\"eventTimeMs\":1586269506179,\"latencyActionTicked\":{\"tickName\":\"adns\",\"clientActionNonce\":\"FkNqj-KfJE3aiu7N\"},\"context\":{\"lastActivityMs\":\"-1\"}},{\"eventTimeMs\":1586269506182,\"latencyActionTicked\":{\"tickName\":\"areq\",\"clientActionNonce\":\"FkNqj-KfJE3aiu7N\"},\"context\":{\"lastActivityMs\":\"-1\"}},{\"eventTimeMs\":1586269506197,\"latencyActionTicked\":{\"tickName\":\"avb\",\"clientActionNonce\":\"FkNqj-KfJE3aiu7N\"},\"context\":{\"lastActivityMs\":\"-1\"}},{\"eventTimeMs\":1586269506219,\"latencyActionTicked\":{\"tickName\":\"arc\",\"clientActionNonce\":\"FkNqj-KfJE3aiu7N\"},\"context\":{\"lastActivityMs\":\"-1\"}},{\"eventTimeMs\":1586269506310,\"latencyActionInfo\":{\"playerType\":\"LATENCY_PLAYER_HTML5\",\"clientActionNonce\":\"FkNqj-KfJE3aiu7N\"},\"context\":{\"lastActivityMs\":\"158\"}},{\"eventTimeMs\":1586269506302,\"latencyActionTicked\":{\"tickName\":\"pbs\",\"clientActionNonce\":\"FkNqj-KfJE3aiu7N\"},\"context\":{\"lastActivityMs\":\"-1\"}},{\"eventTimeMs\":1586269506311,\"latencyActionTicked\":{\"tickName\":\"vr\",\"clientActionNonce\":\"FkNqj-KfJE3aiu7N\"},\"context\":{\"lastActivityMs\":\"158\"}},{\"eventTimeMs\":1586269506311,\"latencyActionInfo\":{\"videoId\":\"8MfD-_YJL9U\",\"clientActionNonce\":\"FkNqj-KfJE3aiu7N\"},\"context\":{\"lastActivityMs\":\"158\"}},{\"eventTimeMs\":1586269506311,\"latencyActionInfo\":{\"clientPlaybackNonce\":\"lmRATwtI0wG9kD1g\",\"clientActionNonce\":\"FkNqj-KfJE3aiu7N\"},\"context\":{\"lastActivityMs\":\"158\"}},{\"eventTimeMs\":1586269506311,\"latencyActionInfo\":{\"playerInfo\":{\"itag\":\"243\"},\"clientActionNonce\":\"FkNqj-KfJE3aiu7N\"},\"context\":{\"lastActivityMs\":\"159\"}},{\"eventTimeMs\":1586269505730,\"latencyActionTicked\":{\"tickName\":\"gv\",\"clientActionNonce\":\"FkNqj-KfJE3aiu7N\"},\"context\":{\"lastActivityMs\":\"-1\"}},{\"eventTimeMs\":1586269506224,\"latencyActionTicked\":{\"tickName\":\"ada\",\"clientActionNonce\":\"FkNqj-KfJE3aiu7N\"},\"context\":{\"lastActivityMs\":\"-1\"}},{\"eventTimeMs\":1586269506234,\"latencyActionTicked\":{\"tickName\":\"vda\",\"clientActionNonce\":\"FkNqj-KfJE3aiu7N\"},\"context\":{\"lastActivityMs\":\"-1\"}},{\"eventTimeMs\":1586269505729,\"latencyActionTicked\":{\"tickName\":\"vri\",\"clientActionNonce\":\"FkNqj-KfJE3aiu7N\"},\"context\":{\"lastActivityMs\":\"-1\"}},{\"eventTimeMs\":1586269505729,\"latencyActionTicked\":{\"tickName\":\"vdns\",\"clientActionNonce\":\"FkNqj-KfJE3aiu7N\"},\"context\":{\"lastActivityMs\":\"-1\"}},{\"eventTimeMs\":1586269506183,\"latencyActionTicked\":{\"tickName\":\"vreq\",\"clientActionNonce\":\"FkNqj-KfJE3aiu7N\"},\"context\":{\"lastActivityMs\":\"-1\"}},{\"eventTimeMs\":1586269506207,\"latencyActionTicked\":{\"tickName\":\"fvb\",\"clientActionNonce\":\"FkNqj-KfJE3aiu7N\"},\"context\":{\"lastActivityMs\":\"-1\"}},{\"eventTimeMs\":1586269506232,\"latencyActionTicked\":{\"tickName\":\"vrc\",\"clientActionNonce\":\"FkNqj-KfJE3aiu7N\"},\"context\":{\"lastActivityMs\":\"-1\"}},{\"eventTimeMs\":1586269505729,\"latencyActionTicked\":{\"tickName\":\"ari\",\"clientActionNonce\":\"FkNqj-KfJE3aiu7N\"},\"context\":{\"lastActivityMs\":\"-1\"}},{\"eventTimeMs\":1586269506179,\"latencyActionTicked\":{\"tickName\":\"adns\",\"clientActionNonce\":\"FkNqj-KfJE3aiu7N\"},\"context\":{\"lastActivityMs\":\"-1\"}},{\"eventTimeMs\":1586269506182,\"latencyActionTicked\":{\"tickName\":\"areq\",\"clientActionNonce\":\"FkNqj-KfJE3aiu7N\"},\"context\":{\"lastActivityMs\":\"-1\"}},{\"eventTimeMs\":1586269506197,\"latencyActionTicked\":{\"tickName\":\"avb\",\"clientActionNonce\":\"FkNqj-KfJE3aiu7N\"},\"context\":{\"lastActivityMs\":\"-1\"}},{\"eventTimeMs\":1586269506219,\"latencyActionTicked\":{\"tickName\":\"arc\",\"clientActionNonce\":\"FkNqj-KfJE3aiu7N\"},\"context\":{\"lastActivityMs\":\"-1\"}},{\"eventTimeMs\":1586269506314,\"adsClientStateChange\":{\"adsClientEvent\":{\"eventType\":\"ADS_CLIENT_EVENT_TYPE_ADPLACEMENTRENDERER_RECEIVED\"}},\"context\":{\"lastActivityMs\":\"162\"}},{\"eventTimeMs\":1586269506314,\"adsClientStateChange\":{\"adsClientEvent\":{\"eventType\":\"ADS_CLIENT_EVENT_TYPE_ADPLACEMENT_SCHEDULED\"}},\"context\":{\"lastActivityMs\":\"162\"}},{\"eventTimeMs\":1586269506314,\"latencyActionBaselined\":{\"clientActionNonce\":\"awlCrnUDXYvdNIzT\"},\"context\":{\"lastActivityMs\":\"162\"}},{\"eventTimeMs\":1586269506314,\"latencyActionInfo\":{\"actionType\":\"LATENCY_ACTION_VIDEO_TO_AD\",\"previousAction\":\"LATENCY_ACTION_WATCH\",\"clientActionNonce\":\"awlCrnUDXYvdNIzT\"},\"context\":{\"lastActivityMs\":\"162\"}},{\"eventTimeMs\":1586269506315,\"latencyActionInfo\":{\"playerType\":\"LATENCY_PLAYER_HTML5\",\"clientActionNonce\":\"awlCrnUDXYvdNIzT\"},\"context\":{\"lastActivityMs\":\"163\"}},{\"eventTimeMs\":1586269506315,\"latencyActionInfo\":{\"playerInfo\":{\"preloadType\":\"2\"},\"clientActionNonce\":\"awlCrnUDXYvdNIzT\"},\"context\":{\"lastActivityMs\":\"163\"}},{\"eventTimeMs\":1586269506315,\"latencyActionInfo\":{\"adBreakType\":\"2\",\"clientActionNonce\":\"awlCrnUDXYvdNIzT\"},\"context\":{\"lastActivityMs\":\"163\"}},{\"eventTimeMs\":1586269506315,\"latencyActionInfo\":{\"clientPlaybackNonce\":\"uHKyTzt7B0k14BPI\",\"clientActionNonce\":\"awlCrnUDXYvdNIzT\"},\"context\":{\"lastActivityMs\":\"163\"}},{\"eventTimeMs\":1586269506315,\"latencyActionInfo\":{\"videoId\":\"6IoYKUqYA8U\",\"clientActionNonce\":\"awlCrnUDXYvdNIzT\"},\"context\":{\"lastActivityMs\":\"163\"}},{\"eventTimeMs\":1586269506315,\"latencyActionInfo\":{\"adClientPlaybackNonce\":\"lmRATwtI0wG9kD1g\",\"clientActionNonce\":\"awlCrnUDXYvdNIzT\"},\"context\":{\"lastActivityMs\":\"163\"}},{\"eventTimeMs\":1586269506315,\"latencyActionInfo\":{\"adVideoId\":\"8MfD-_YJL9U\",\"clientActionNonce\":\"awlCrnUDXYvdNIzT\"},\"context\":{\"lastActivityMs\":\"163\"}},{\"eventTimeMs\":1586269506316,\"latencyActionInfo\":{\"videoStreamType\":\"VIDEO_STREAM_TYPE_VOD\",\"clientActionNonce\":\"awlCrnUDXYvdNIzT\"},\"context\":{\"lastActivityMs\":\"163\"}},{\"eventTimeMs\":1586269506316,\"latencyActionInfo\":{\"adType\":\"15_2_1\",\"clientActionNonce\":\"awlCrnUDXYvdNIzT\"},\"context\":{\"lastActivityMs\":\"163\"}},{\"eventTimeMs\":1586269506346,\"latencyActionInfo\":{\"videoId\":\"8MfD-_YJL9U\",\"clientActionNonce\":\"FkNqj-KfJE3aiu7N\"},\"context\":{\"lastActivityMs\":\"194\"}},{\"eventTimeMs\":1586269506346,\"latencyActionInfo\":{\"clientPlaybackNonce\":\"lmRATwtI0wG9kD1g\",\"clientActionNonce\":\"FkNqj-KfJE3aiu7N\"},\"context\":{\"lastActivityMs\":\"194\"}},{\"eventTimeMs\":1586269506346,\"latencyActionInfo\":{\"playerInfo\":{\"itag\":\"243\"},\"clientActionNonce\":\"FkNqj-KfJE3aiu7N\"},\"context\":{\"lastActivityMs\":\"194\"}},{\"eventTimeMs\":1586269505730,\"latencyActionTicked\":{\"tickName\":\"gv\",\"clientActionNonce\":\"FkNqj-KfJE3aiu7N\"},\"context\":{\"lastActivityMs\":\"-1\"}},{\"eventTimeMs\":1586269506224,\"latencyActionTicked\":{\"tickName\":\"ada\",\"clientActionNonce\":\"FkNqj-KfJE3aiu7N\"},\"context\":{\"lastActivityMs\":\"-1\"}},{\"eventTimeMs\":1586269506234,\"latencyActionTicked\":{\"tickName\":\"vda\",\"clientActionNonce\":\"FkNqj-KfJE3aiu7N\"},\"context\":{\"lastActivityMs\":\"-1\"}},{\"eventTimeMs\":1586269505729,\"latencyActionTicked\":{\"tickName\":\"vri\",\"clientActionNonce\":\"FkNqj-KfJE3aiu7N\"},\"context\":{\"lastActivityMs\":\"-1\"}},{\"eventTimeMs\":1586269505729,\"latencyActionTicked\":{\"tickName\":\"vdns\",\"clientActionNonce\":\"FkNqj-KfJE3aiu7N\"},\"context\":{\"lastActivityMs\":\"-1\"}},{\"eventTimeMs\":1586269506183,\"latencyActionTicked\":{\"tickName\":\"vreq\",\"clientActionNonce\":\"FkNqj-KfJE3aiu7N\"},\"context\":{\"lastActivityMs\":\"-1\"}},{\"eventTimeMs\":1586269506207,\"latencyActionTicked\":{\"tickName\":\"fvb\",\"clientActionNonce\":\"FkNqj-KfJE3aiu7N\"},\"context\":{\"lastActivityMs\":\"-1\"}},{\"eventTimeMs\":1586269506232,\"latencyActionTicked\":{\"tickName\":\"vrc\",\"clientActionNonce\":\"FkNqj-KfJE3aiu7N\"},\"context\":{\"lastActivityMs\":\"-1\"}},{\"eventTimeMs\":1586269505729,\"latencyActionTicked\":{\"tickName\":\"ari\",\"clientActionNonce\":\"FkNqj-KfJE3aiu7N\"},\"context\":{\"lastActivityMs\":\"-1\"}},{\"eventTimeMs\":1586269506179,\"latencyActionTicked\":{\"tickName\":\"adns\",\"clientActionNonce\":\"FkNqj-KfJE3aiu7N\"},\"context\":{\"lastActivityMs\":\"-1\"}},{\"eventTimeMs\":1586269506182,\"latencyActionTicked\":{\"tickName\":\"areq\",\"clientActionNonce\":\"FkNqj-KfJE3aiu7N\"},\"context\":{\"lastActivityMs\":\"-1\"}},{\"eventTimeMs\":1586269506197,\"latencyActionTicked\":{\"tickName\":\"avb\",\"clientActionNonce\":\"FkNqj-KfJE3aiu7N\"},\"context\":{\"lastActivityMs\":\"-1\"}},{\"eventTimeMs\":1586269506219,\"latencyActionTicked\":{\"tickName\":\"arc\",\"clientActionNonce\":\"FkNqj-KfJE3aiu7N\"},\"context\":{\"lastActivityMs\":\"-1\"}},{\"eventTimeMs\":1586269506537,\"latencyActionTicked\":{\"tickName\":\"nc3\",\"clientActionNonce\":\"FkNqj-KfJE3aiu7N\"},\"context\":{\"lastActivityMs\":\"385\"}},{\"eventTimeMs\":1586269506537,\"latencyActionTicked\":{\"tickName\":\"nc4\",\"clientActionNonce\":\"FkNqj-KfJE3aiu7N\"},\"context\":{\"lastActivityMs\":\"385\"}},{\"eventTimeMs\":1586269506546,\"latencyActionTicked\":{\"tickName\":\"np3\",\"clientActionNonce\":\"FkNqj-KfJE3aiu7N\"},\"context\":{\"lastActivityMs\":\"394\"}},{\"eventTimeMs\":1586269505188,\"latencyActionTicked\":{\"tickName\":\"srt\",\"clientActionNonce\":\"FkNqj-KfJE3aiu7N\"},\"context\":{\"lastActivityMs\":\"-1\"}},{\"eventTimeMs\":1586269506547,\"latencyActionTicked\":{\"tickName\":\"pdc\",\"clientActionNonce\":\"FkNqj-KfJE3aiu7N\"},\"context\":{\"lastActivityMs\":\"394\"}},{\"eventTimeMs\":1586269506547,\"latencyActionInfo\":{\"serverTimeMs\":1329,\"clientActionNonce\":\"FkNqj-KfJE3aiu7N\"},\"context\":{\"lastActivityMs\":\"394\"}},{\"eventTimeMs\":1586269506547,\"latencyActionInfo\":{\"isMonetized\":true,\"clientActionNonce\":\"FkNqj-KfJE3aiu7N\"},\"context\":{\"lastActivityMs\":\"395\"}},{\"eventTimeMs\":1586269506547,\"latencyActionInfo\":{\"getPlayerRequestId\":\"0x100dbabaf379ed72\",\"clientActionNonce\":\"FkNqj-KfJE3aiu7N\"},\"context\":{\"lastActivityMs\":\"395\"}},{\"eventTimeMs\":1586269506547,\"latencyActionInfo\":{\"getWatchNextRequestId\":\"0x100dbabaf379ed72\",\"clientActionNonce\":\"FkNqj-KfJE3aiu7N\"},\"context\":{\"lastActivityMs\":\"395\"}},{\"eventTimeMs\":1586269506548,\"latencyActionTicked\":{\"tickName\":\"nd\",\"clientActionNonce\":\"FkNqj-KfJE3aiu7N\"},\"context\":{\"lastActivityMs\":\"395\"}},{\"eventTimeMs\":1586269506548,\"visualElementAttached\":{\"csn\":\"QY2MXpLgCMXO7ASV3aXQBw\",\"parentVe\":{\"veType\":3832},\"childVes\":[{\"trackingParams\":\"CAAQumkiEwiN_fisi9boAhWVW7IKHf25DOc=\"}]},\"context\":{\"lastActivityMs\":\"396\"}},{\"eventTimeMs\":1586269506563,\"latencyActionTicked\":{\"tickName\":\"np4\",\"clientActionNonce\":\"FkNqj-KfJE3aiu7N\"},\"context\":{\"lastActivityMs\":\"411\"}},{\"eventTimeMs\":1586269506564,\"latencyActionTicked\":{\"tickName\":\"lps\",\"clientActionNonce\":\"FkNqj-KfJE3aiu7N\"},\"context\":{\"lastActivityMs\":\"411\"}},{\"eventTimeMs\":1586269506565,\"latencyActionInfo\":{\"isNavigation\":true,\"clientActionNonce\":\"FkNqj-KfJE3aiu7N\"},\"context\":{\"lastActivityMs\":\"412\"}},{\"eventTimeMs\":1586269506565,\"latencyActionInfo\":{\"clientScreenNonce\":\"QY2MXpLgCMXO7ASV3aXQBw\",\"clientActionNonce\":\"FkNqj-KfJE3aiu7N\"},\"context\":{\"lastActivityMs\":\"412\"}},{\"eventTimeMs\":1586269506565,\"latencyActionInfo\":{\"httpProtocol\":\"h2\",\"clientActionNonce\":\"FkNqj-KfJE3aiu7N\"},\"context\":{\"lastActivityMs\":\"412\"}},{\"eventTimeMs\":1586269506565,\"latencyActionInfo\":{\"transportProtocol\":\"tcp\",\"clientActionNonce\":\"FkNqj-KfJE3aiu7N\"},\"context\":{\"lastActivityMs\":\"412\"}},{\"eventTimeMs\":1586269506565,\"latencyActionInfo\":{\"isVisible\":true,\"clientActionNonce\":\"FkNqj-KfJE3aiu7N\"},\"context\":{\"lastActivityMs\":\"412\"}},{\"eventTimeMs\":1586269506565,\"latencyActionInfo\":{\"actionType\":\"LATENCY_ACTION_WATCH\",\"previousAction\":\"LATENCY_ACTION_WATCH\",\"clientActionNonce\":\"FkNqj-KfJE3aiu7N\"},\"context\":{\"lastActivityMs\":\"413\"}},{\"eventTimeMs\":1586269506571,\"latencyActionInfo\":{\"watchInfo\":{\"isPlaylist\":true},\"clientActionNonce\":\"FkNqj-KfJE3aiu7N\"},\"context\":{\"lastActivityMs\":\"419\"}},{\"eventTimeMs\":1586269506571,\"latencyActionTicked\":{\"tickName\":\"pdl\",\"clientActionNonce\":\"FkNqj-KfJE3aiu7N\"},\"context\":{\"lastActivityMs\":\"419\"}},{\"eventTimeMs\":1586269506661,\"latencyActionTicked\":{\"tickName\":\"pda\",\"clientActionNonce\":\"FkNqj-KfJE3aiu7N\"},\"context\":{\"lastActivityMs\":\"509\"}},{\"eventTimeMs\":1586269506679,\"visualElementShown\":{\"csn\":\"QY2MXpLgCMXO7ASV3aXQBw\",\"ve\":{\"trackingParams\":\"CBkQ7VAiEwj8qv6ywtboAhWHNJsKHefFB5g=\"},\"eventType\":1},\"context\":{\"lastActivityMs\":\"527\"}},{\"eventTimeMs\":1586269506680,\"visualElementShown\":{\"csn\":\"QY2MXpLgCMXO7ASV3aXQBw\",\"ve\":{\"trackingParams\":\"CAEQq6wBIhMI_Kr-ssLW6AIVhzSbCh3nxQeY\"},\"eventType\":1},\"context\":{\"lastActivityMs\":\"528\"}},{\"eventTimeMs\":1586269506681,\"visualElementShown\":{\"csn\":\"QY2MXpLgCMXO7ASV3aXQBw\",\"ve\":{\"trackingParams\":\"CBoQsV4iEwj8qv6ywtboAhWHNJsKHefFB5g=\"},\"eventType\":1},\"context\":{\"lastActivityMs\":\"528\"}},{\"eventTimeMs\":1586269506681,\"visualElementShown\":{\"csn\":\"QY2MXpLgCMXO7ASV3aXQBw\",\"ve\":{\"trackingParams\":\"CBkQ7VAiEwj8qv6ywtboAhWHNJsKHefFB5g=\"},\"eventType\":1},\"context\":{\"lastActivityMs\":\"528\"}},{\"eventTimeMs\":1586269506681,\"visualElementShown\":{\"csn\":\"QY2MXpLgCMXO7ASV3aXQBw\",\"ve\":{\"trackingParams\":\"CBQQ_qsBGAAiEwj8qv6ywtboAhWHNJsKHefFB5g=\"},\"eventType\":1},\"context\":{\"lastActivityMs\":\"529\"}},{\"eventTimeMs\":1586269506681,\"visualElementShown\":{\"csn\":\"QY2MXpLgCMXO7ASV3aXQBw\",\"ve\":{\"trackingParams\":\"CAoQ_qsBGAEiEwj8qv6ywtboAhWHNJsKHefFB5g=\"},\"eventType\":1},\"context\":{\"lastActivityMs\":\"529\"}},{\"eventTimeMs\":1586269506681,\"visualElementShown\":{\"csn\":\"QY2MXpLgCMXO7ASV3aXQBw\",\"ve\":{\"trackingParams\":\"CAgQ_qsBGAIiEwj8qv6ywtboAhWHNJsKHefFB5g=\"},\"eventType\":1},\"context\":{\"lastActivityMs\":\"529\"}},{\"eventTimeMs\":1586269506681,\"visualElementShown\":{\"csn\":\"QY2MXpLgCMXO7ASV3aXQBw\",\"ve\":{\"trackingParams\":\"CAcQ1IAEGAMiEwj8qv6ywtboAhWHNJsKHefFB5g=\"},\"eventType\":1},\"context\":{\"lastActivityMs\":\"529\"}},{\"eventTimeMs\":1586269506681,\"visualElementShown\":{\"csn\":\"QY2MXpLgCMXO7ASV3aXQBw\",\"ve\":{\"trackingParams\":\"CAAQg2ciEwj8qv6ywtboAhWHNJsKHefFB5g=\"},\"eventType\":1},\"context\":{\"lastActivityMs\":\"529\"}},{\"eventTimeMs\":1586269506681,\"visualElementShown\":{\"csn\":\"QY2MXpLgCMXO7ASV3aXQBw\",\"ve\":{\"trackingParams\":\"CCoQ8DIiEwj8qv6ywtboAhWHNJsKHefFB5g=\"},\"eventType\":1},\"context\":{\"lastActivityMs\":\"529\"}},{\"eventTimeMs\":1586269506681,\"visualElementShown\":{\"csn\":\"QY2MXpLgCMXO7ASV3aXQBw\",\"ve\":{\"trackingParams\":\"CCsQiPkBGFciEwj8qv6ywtboAhWHNJsKHefFB5g=\"},\"eventType\":1},\"context\":{\"lastActivityMs\":\"529\"}},{\"eventTimeMs\":1586269506682,\"visualElementShown\":{\"csn\":\"QY2MXpLgCMXO7ASV3aXQBw\",\"ve\":{\"trackingParams\":\"CI0BEMggGEMiEwj8qv6ywtboAhWHNJsKHefFB5g=\"},\"eventType\":1},\"context\":{\"lastActivityMs\":\"530\"}},{\"eventTimeMs\":1586269506682,\"visualElementShown\":{\"csn\":\"QY2MXpLgCMXO7ASV3aXQBw\",\"ve\":{\"trackingParams\":\"CI8BEOSbBRgEIhMI_Kr-ssLW6AIVhzSbCh3nxQeY\"},\"eventType\":1},\"context\":{\"lastActivityMs\":\"530\"}},{\"eventTimeMs\":1586269506682,\"visualElementShown\":{\"csn\":\"QY2MXpLgCMXO7ASV3aXQBw\",\"ve\":{\"trackingParams\":\"CIgBEMggGEQiEwj8qv6ywtboAhWHNJsKHefFB5g=\"},\"eventType\":1},\"context\":{\"lastActivityMs\":\"530\"}},{\"eventTimeMs\":1586269506682,\"visualElementShown\":{\"csn\":\"QY2MXpLgCMXO7ASV3aXQBw\",\"ve\":{\"trackingParams\":\"CIoBEOSbBRgEIhMI_Kr-ssLW6AIVhzSbCh3nxQeY\"},\"eventType\":1},\"context\":{\"lastActivityMs\":\"530\"}},{\"eventTimeMs\":1586269506700,\"latencyActionTicked\":{\"tickName\":\"bcp\",\"clientActionNonce\":\"FkNqj-KfJE3aiu7N\"},\"context\":{\"lastActivityMs\":\"548\"}},{\"eventTimeMs\":1586269506718,\"latencyActionTicked\":{\"tickName\":\"cpt\",\"clientActionNonce\":\"FkNqj-KfJE3aiu7N\"},\"context\":{\"lastActivityMs\":\"566\"}},{\"eventTimeMs\":1586261014186,\"latencyActionTicked\":{\"tickName\":\"vpl\",\"clientActionNonce\":\"FkNqj-KfJE3aiu7N\"},\"context\":{\"lastActivityMs\":\"-1\"}},{\"eventTimeMs\":1586269506718,\"latencyActionTicked\":{\"tickName\":\"ol\",\"clientActionNonce\":\"FkNqj-KfJE3aiu7N\"},\"context\":{\"lastActivityMs\":\"-1\"}},{\"eventTimeMs\":1586269507588,\"latencyActionTicked\":{\"tickName\":\"cmi\",\"clientActionNonce\":\"FkNqj-KfJE3aiu7N\"},\"context\":{\"lastActivityMs\":\"1436\"}},{\"eventTimeMs\":1586269511505,\"visualElementShown\":{\"csn\":\"QY2MXpLgCMXO7ASV3aXQBw\",\"ve\":{\"trackingParams\":\"CEMQkKwCIhMIwZX-ssLW6AIVBclcCh0mbg5e\"},\"eventType\":1},\"context\":{\"lastActivityMs\":\"5352\"}}],\"requestTimeMs\":1586269517589,\"serializedClientEventId\":{\"serializedEventId\":\"qFKMXquMLNKhyQW6_4qIAw\",\"clientCounter\":25596}}\n", "webapp_id": "56d69c95-2cc0-4da5-92e3-b514f3681932", "src_port": 44332, "raw_uri": "https://www.youtube.com/youtubei/v1/log_event?alt=json&key=AIzaSyAO_FJ2SlqU8Q4STEHLGCilw_Y9_11qcW8", "obj_id": "2fa8fc73-2fc0-4e6b-9200-47a3d66c5b5e", "uri": {"username": "", "password": "", "fragment": "", "hostname": "www.youtube.com", "path": "/youtubei/v1/log_event", "query": "alt=json&key=AIzaSyAO_FJ2SlqU8Q4STEHLGCilw_Y9_11qcW8", "scheme": "https", "port": -1}, "method": "POST", "src_ip": "10.0.0.14", "headers": [[":method", "POST"], [":authority", "www.youtube.com"], [":scheme", "https"], [":path", "/youtubei/v1/log_event?alt=json&key=AIzaSyAO_FJ2SlqU8Q4STEHLGCilw_Y9_11qcW8"], ["content-length", "17125"], ["x-youtube-device", "cbr=Chrome&cbrver=80.0.3987.0&ceng=WebKit&cengver=537.36&cos=X11"], ["x-youtube-page-label", "youtube.ytfe.desktop_20200403_4_RC1"], ["user-agent", "Mozilla/5.0 (X11; Linux x86_64) AppleWebKit/537.36 (KHTML, like Gecko) Chrome/80.0.3987.0 Safari/537.36"], ["x-youtube-variants-checksum", "0af5de4b0965d6a165d5479195808fbb"], ["content-type", "application/json"], ["x-youtube-page-cl", "304735510"], ["x-youtube-utc-offset", "180"], ["x-youtube-client-name", "1"], ["x-youtube-client-version", "2.20200404.04.01"], ["sec-fetch-dest", "empty"], ["x-youtube-time-zone", "Europe/Moscow"], ["x-goog-visitor-id", "Cgt2TS04TTVBbnkwWSjBmrL0BQ%3D%3D"], ["x-youtube-ad-signals", "dt=1586254505492&flash=0&frm&u_tz=180&u_his=50&u_java&u_h=1080&u_w=1920&u_ah=1080&u_aw=1920&u_cd=24&u_nplug=3&u_nmime=4&bc=31&bih=600&biw=785&brdim=10%2C10%2C10%2C10%2C1920%2C0%2C945%2C1037%2C800%2C600&vis=1&wgl=true&ca_type=image&bid=ANyPxKpNpHdvvS7cHUYVnXu-CGpHPlwpLy_kwzOBof9rw0BDbuTuh3WKuUJK1UVaCVd9ViFjmumHDkgcR7h4r_XPUkaVt5MIWw"], ["accept", "*/*"], ["origin", "https://www.youtube.com"], ["sec-fetch-site", "same-origin"], ["sec-fetch-mode", "cors"], ["referer", "https://www.youtube.com/watch?v=6IoYKUqYA8U&list=TLPQMDcwNDIwMjD3jbEp8sFFOQ&index=72"], ["accept-encoding", "gzip, deflate, br"], ["accept-language", "ru-RU,ru;q=0.9,en-US;q=0.8,en;q=0.7"], ["cookie", "YSC=1fh7DCvtNmk; VISITOR_INFO1_LIVE=vM-8M5Any0Y; GPS=1"]], "dst_port": 80, "protocol": 1.1, "dst_ip": "10.72.55.226"}