{"body": "{\"events\":[{\"attributes\":{\"app_version\":\"2.0.0\",\"device_type\":\"desktop\",\"namespace\":\"bx\",\"platform\":\"site\",\"screen_resolution_x\":1920,\"screen_resolution_y\":1080},\"page\":{\"category_id\":0,\"current\":\"cart\",\"current_url\":\"/cart\",\"page_view_id\":\"8f15bc50-7b97-453e-a194-d2eca50507db\",\"previous\":\"category\",\"previous_page_view_id\":\"bb4eafb5-cedb-4a44-b7e9-eb067434936f\",\"referral_url\":\"/category/literatura-dlya-podrostkov-33015/?page=3\",\"layout_id\":4803,\"layout_version\":76,\"rule_id\":4757},\"special\":true,\"timestamp\":\"2020-03-24 12:58:07 +0300\",\"user\":{\"ab_group\":24,\"client_id\":0,\"experiments\":\"219:221,318:438,320:444,326:486,327:487,328:480,332:528,338:550,345:568,346:571,347:572,348:575\",\"google_id\":\"GA1.2.1657344491.1585042046\",\"latitude\":55.755814,\"long_cookie\":\"53ebd41441e6049b016281d59dc38ea7\",\"longitude\":37.617634,\"region_id\":2,\"session_id\":\"g7f8O9KUQK+7aw6nLff3Qw\"}},{\"action_type\":\"remove\",\"composer\":{\"slice\":{},\"cell\":{\"type\":\"product\",\"deliveryType\":\"FBO\",\"sellerId\":782,\"quantity\":1,\"originalPrice\":294,\"finalPrice\":229,\"index\":5,\"stock\":1,\"storehouseId\":660,\"categoryId\":40040,\"id\":149103313,\"title\":\"\u041f\u0430\u043d\u0434\u0435\u043c\u043e\u043d\u0438\u0443\u043c. \u041b\u0430\u0440\u0435\u0446, \u043f\u043e\u043b\u043d\u044b\u0439 \u0442\u044c\u043c\u044b. \u041a\u043d\u0438\u0433\u0430 5.\",\"isSupermarket\":false}},\"number\":312,\"timestamp\":\"2020-03-24 12:58:29 +0300\",\"uuid\":\"7a5b419b-fad5-4da7-b4ce-633d0b4c4cda\",\"version\":\"2\",\"widget\":{\"type\":\"cart\",\"name\":\"cart.controls\",\"id\":206862,\"revision_id\":139019,\"config_revision_id\":0,\"index\":26}},{\"action_type\":\"remove\",\"composer\":{\"slice\":{},\"cell\":{\"type\":\"product\",\"deliveryType\":\"FBO\",\"sellerId\":782,\"quantity\":1,\"originalPrice\":294,\"finalPrice\":229,\"index\":5,\"stock\":1,\"storehouseId\":660,\"categoryId\":40040,\"id\":159896252,\"title\":\"\u041f\u0430\u043d\u0434\u0435\u043c\u043e\u043d\u0438\u0443\u043c. \u0412\u0440\u0435\u043c\u044f \u0422\u0435\u043c\u043d\u044b\u0445 \u041e\u0445\u043e\u0442\u043d\u0438\u043a\u043e\u0432. \u041a\u043d\u0438\u0433\u0430 7.\",\"isSupermarket\":false}},\"number\":313,\"timestamp\":\"2020-03-24 12:58:29 +0300\",\"uuid\":\"a817df59-cb87-4432-87b0-224b9e7214e8\",\"version\":\"2\",\"widget\":{\"type\":\"cart\",\"name\":\"cart.controls\",\"id\":206862,\"revision_id\":139019,\"config_revision_id\":0,\"index\":26}},{\"action_type\":\"remove\",\"composer\":{\"slice\":{},\"cell\":{\"type\":\"product\",\"deliveryType\":\"FBO\",\"sellerId\":782,\"quantity\":1,\"originalPrice\":2272,\"finalPrice\":2272,\"index\":5,\"stock\":1,\"storehouseId\":660,\"categoryId\":40040,\"id\":149639549,\"title\":\"\u0414\u0430\u0440\u0438\u0442\u0435\u043b\u0438 (\u043f\u043e\u0434\u0430\u0440\u043e\u0447\u043d\u044b\u0439 \u043a\u043e\u043c\u043f\u043b\u0435\u043a\u0442 \u0438\u0437 5 \u043a\u043d\u0438\u0433) | \u0421\u043e\u0431\u043e\u043b\u044c \u0415\u043a\u0430\u0442\u0435\u0440\u0438\u043d\u0430\",\"isSupermarket\":false}},\"number\":314,\"timestamp\":\"2020-03-24 12:58:29 +0300\",\"uuid\":\"74c544de-ac91-4c68-9015-22e3bd1114ca\",\"version\":\"2\",\"widget\":{\"type\":\"cart\",\"name\":\"cart.controls\",\"id\":206862,\"revision_id\":139019,\"config_revision_id\":0,\"index\":26}},{\"action_type\":\"remove\",\"composer\":{\"slice\":{},\"cell\":{\"type\":\"product\",\"deliveryType\":\"FBO\",\"sellerId\":782,\"quantity\":1,\"originalPrice\":454,\"finalPrice\":454,\"index\":5,\"stock\":1,\"storehouseId\":660,\"categoryId\":40040,\"id\":148803723,\"title\":\"\u0427\u0430\u0441\u043e\u0434\u0435\u0438. \u0427\u0430\u0441\u043e\u0432\u0430\u044f \u0431\u0430\u0448\u043d\u044f. \u041a\u043d\u0438\u0433\u0430 3 | \u0429\u0435\u0440\u0431\u0430 \u041d\u0430\u0442\u0430\u043b\u044c\u044f \u0412\u0430\u0441\u0438\u043b\u044c\u0435\u0432\u043d\u0430\",\"isSupermarket\":false}},\"number\":315,\"timestamp\":\"2020-03-24 12:58:29 +0300\",\"uuid\":\"f9702109-fe9b-46b0-9716-05af69534e6e\",\"version\":\"2\",\"widget\":{\"type\":\"cart\",\"name\":\"cart.controls\",\"id\":206862,\"revision_id\":139019,\"config_revision_id\":0,\"index\":26}},{\"action_type\":\"remove\",\"composer\":{\"slice\":{},\"cell\":{\"type\":\"product\",\"deliveryType\":\"FBO\",\"sellerId\":782,\"quantity\":1,\"originalPrice\":491,\"finalPrice\":382,\"index\":5,\"stock\":1,\"storehouseId\":660,\"categoryId\":40040,\"id\":148803705,\"title\":\"\u042d\u0440\u0430\u0433\u043e\u043d. \u0412\u043e\u0437\u0432\u0440\u0430\u0449\u0435\u043d\u0438\u0435. \u041a\u043d\u0438\u0433\u0430 2. | \u041f\u0430\u043e\u043b\u0438\u043d\u0438 \u041a\u0440\u0438\u0441\u0442\u043e\u0444\u0435\u0440\",\"isSupermarket\":false}},\"number\":316,\"timestamp\":\"2020-03-24 12:58:30 +0300\",\"uuid\":\"464f9ae2-db22-495c-bc29-8078d76f94c8\",\"version\":\"2\",\"widget\":{\"type\":\"cart\",\"name\":\"cart.controls\",\"id\":206862,\"revision_id\":139019,\"config_revision_id\":0,\"index\":26}},{\"action_type\":\"remove\",\"composer\":{\"slice\":{},\"cell\":{\"type\":\"product\",\"deliveryType\":\"FBO\",\"sellerId\":782,\"quantity\":1,\"originalPrice\":454,\"finalPrice\":354,\"index\":5,\"stock\":1,\"storehouseId\":660,\"categoryId\":40040,\"id\":148804024,\"title\":\"\u041f\u0430\u0440\u0434\u0443\u0441. \u0411\u0435\u0433\u0443\u0449\u0438\u0439 \u0432 \u043d\u043e\u0447\u0438. \u041a\u043d\u0438\u0433\u0430 1. | \u0413\u0430\u0433\u043b\u043e\u0435\u0432 \u0415\u0432\u0433\u0435\u043d\u0438\u0439\",\"isSupermarket\":false}},\"number\":317,\"timestamp\":\"2020-03-24 12:58:30 +0300\",\"uuid\":\"302ca7a8-36fa-4385-8e84-804b027a5927\",\"version\":\"2\",\"widget\":{\"type\":\"cart\",\"name\":\"cart.controls\",\"id\":206862,\"revision_id\":139019,\"config_revision_id\":0,\"index\":26}},{\"action_type\":\"remove\",\"composer\":{\"slice\":{},\"cell\":{\"type\":\"product\",\"deliveryType\":\"FBO\",\"sellerId\":782,\"quantity\":1,\"originalPrice\":454,\"finalPrice\":454,\"index\":5,\"stock\":1,\"storehouseId\":660,\"categoryId\":40040,\"id\":148803795,\"title\":\"\u0427\u0430\u0441\u043e\u0434\u0435\u0438. \u0427\u0430\u0441\u043e\u0432\u043e\u0435 \u0438\u043c\u044f. \u041a\u043d\u0438\u0433\u0430 4 | \u0429\u0435\u0440\u0431\u0430 \u041d\u0430\u0442\u0430\u043b\u044c\u044f \u0412\u0430\u0441\u0438\u043b\u044c\u0435\u0432\u043d\u0430\",\"isSupermarket\":false}},\"number\":318,\"timestamp\":\"2020-03-24 12:58:30 +0300\",\"uuid\":\"d70e397a-a1db-4d9b-a51b-e7a555ff61ae\",\"version\":\"2\",\"widget\":{\"type\":\"cart\",\"name\":\"cart.controls\",\"id\":206862,\"revision_id\":139019,\"config_revision_id\":0,\"index\":26}},{\"action_type\":\"remove\",\"composer\":{\"slice\":{},\"cell\":{\"type\":\"product\",\"deliveryType\":\"FBO\",\"sellerId\":782,\"quantity\":1,\"originalPrice\":454,\"finalPrice\":454,\"index\":5,\"stock\":1,\"storehouseId\":660,\"categoryId\":40040,\"id\":148803797,\"title\":\"\u0427\u0430\u0441\u043e\u0434\u0435\u0438. \u0427\u0430\u0441\u043e\u0432\u0430\u044f \u0431\u0438\u0442\u0432\u0430. \u041a\u043d\u0438\u0433\u0430 6 | \u0429\u0435\u0440\u0431\u0430 \u041d\u0430\u0442\u0430\u043b\u044c\u044f \u0412\u0430\u0441\u0438\u043b\u044c\u0435\u0432\u043d\u0430\",\"isSupermarket\":false}},\"number\":319,\"timestamp\":\"2020-03-24 12:58:30 +0300\",\"uuid\":\"036eaa16-09bf-4b88-8fdd-91789a76923c\",\"version\":\"2\",\"widget\":{\"type\":\"cart\",\"name\":\"cart.controls\",\"id\":206862,\"revision_id\":139019,\"config_revision_id\":0,\"index\":26}},{\"action_type\":\"remove\",\"composer\":{\"slice\":{},\"cell\":{\"type\":\"product\",\"deliveryType\":\"FBO\",\"sellerId\":782,\"quantity\":1,\"originalPrice\":454,\"finalPrice\":354,\"index\":5,\"stock\":1,\"storehouseId\":660,\"categoryId\":40040,\"id\":148803796,\"title\":\"\u0427\u0430\u0441\u043e\u0434\u0435\u0438. \u0427\u0430\u0441\u043e\u0433\u0440\u0430\u043c\u043c\u0430. \u041a\u043d\u0438\u0433\u0430 5. | \u0429\u0435\u0440\u0431\u0430 \u041d\u0430\u0442\u0430\u043b\u044c\u044f \u0412\u0430\u0441\u0438\u043b\u044c\u0435\u0432\u043d\u0430\",\"isSupermarket\":false}},\"number\":320,\"timestamp\":\"2020-03-24 12:58:30 +0300\",\"uuid\":\"ff6eec84-0a05-4c5c-91de-c65d68cc8a5c\",\"version\":\"2\",\"widget\":{\"type\":\"cart\",\"name\":\"cart.controls\",\"id\":206862,\"revision_id\":139019,\"config_revision_id\":0,\"index\":26}},{\"action_type\":\"remove\",\"composer\":{\"slice\":{},\"cell\":{\"type\":\"product\",\"deliveryType\":\"FBO\",\"sellerId\":782,\"quantity\":1,\"originalPrice\":454,\"finalPrice\":354,\"index\":5,\"stock\":1,\"storehouseId\":660,\"categoryId\":40040,\"id\":149103314,\"title\":\"\u0418\u043d\u0441\u043e\u043c\u043d\u0438\u044f. \u0414\u0435\u0432\u043e\u0447\u043a\u0430, \u043a\u043e\u0442\u043e\u0440\u0430\u044f \u0441\u043f\u0438\u0442. \u041a\u043d\u0438\u0433\u0430 1.\",\"isSupermarket\":false}},\"number\":321,\"timestamp\":\"2020-03-24 12:58:30 +0300\",\"uuid\":\"644cfe36-fc29-4d7c-bc04-716b834c7c0f\",\"version\":\"2\",\"widget\":{\"type\":\"cart\",\"name\":\"cart.controls\",\"id\":206862,\"revision_id\":139019,\"config_revision_id\":0,\"index\":26}},{\"action_type\":\"remove\",\"composer\":{\"slice\":{},\"cell\":{\"type\":\"product\",\"deliveryType\":\"FBO\",\"sellerId\":782,\"quantity\":1,\"originalPrice\":2726,\"finalPrice\":2726,\"index\":5,\"stock\":1,\"storehouseId\":660,\"categoryId\":40040,\"id\":149639803,\"title\":\"\u0427\u0430\u0441\u043e\u0434\u0435\u0438. \u041f\u043e\u0434\u0430\u0440\u043e\u0447\u043d\u044b\u0439 \u043a\u043e\u043c\u043f\u043b\u0435\u043a\u0442 \u0438\u0437 6 \u043a\u043d\u0438\u0433.\",\"isSupermarket\":false}},\"number\":322,\"timestamp\":\"2020-03-24 12:58:30 +0300\",\"uuid\":\"1e210a57-25ee-4416-9c3b-b06372d035cc\",\"version\":\"2\",\"widget\":{\"type\":\"cart\",\"name\":\"cart.controls\",\"id\":206862,\"revision_id\":139019,\"config_revision_id\":0,\"index\":26}},{\"action_type\":\"remove\",\"composer\":{\"slice\":{},\"cell\":{\"type\":\"product\",\"deliveryType\":\"FBO\",\"sellerId\":782,\"quantity\":1,\"originalPrice\":1817,\"finalPrice\":1417,\"index\":5,\"stock\":1,\"storehouseId\":660,\"categoryId\":40040,\"id\":161613722,\"title\":\"\u041b\u0443\u043d\u0430\u0441\u0442\u0440\u044b. \u041f\u043e\u0434\u0430\u0440\u043e\u0447\u043d\u044b\u0439 \u043d\u0430\u0431\u043e\u0440 \",\"isSupermarket\":false}},\"number\":323,\"timestamp\":\"2020-03-24 12:58:30 +0300\",\"uuid\":\"49314a04-38b4-4191-abd9-c908bb194d7d\",\"version\":\"2\",\"widget\":{\"type\":\"cart\",\"name\":\"cart.controls\",\"id\":206862,\"revision_id\":139019,\"config_revision_id\":0,\"index\":26}},{\"action_type\":\"remove\",\"composer\":{\"slice\":{},\"cell\":{\"type\":\"product\",\"deliveryType\":\"FBO\",\"sellerId\":782,\"quantity\":1,\"originalPrice\":727,\"finalPrice\":567,\"index\":5,\"stock\":1,\"storehouseId\":660,\"categoryId\":40040,\"id\":159905758,\"title\":\"\u0427\u0430\u0440\u043e\u0434\u043e\u043b. \u0412\u0435\u0441\u044c \u0446\u0438\u043a\u043b \u0432 \u043e\u0434\u043d\u043e\u043c \u0442\u043e\u043c\u0435.\",\"isSupermarket\":false}},\"number\":324,\"timestamp\":\"2020-03-24 12:58:30 +0300\",\"uuid\":\"f8d804f7-52e8-4e74-8c57-2f303d780af7\",\"version\":\"2\",\"widget\":{\"type\":\"cart\",\"name\":\"cart.controls\",\"id\":206862,\"revision_id\":139019,\"config_revision_id\":0,\"index\":26}},{\"action_type\":\"remove\",\"composer\":{\"slice\":{},\"cell\":{\"type\":\"product\",\"deliveryType\":\"FBO\",\"sellerId\":782,\"quantity\":1,\"originalPrice\":488,\"finalPrice\":380,\"index\":5,\"stock\":1,\"storehouseId\":660,\"categoryId\":40040,\"id\":149639524,\"title\":\"\u0427\u0430\u0441\u043e\u0434\u0435\u0438. \u041a\u043e\u0440\u043e\u043b\u0435\u0432\u0430 \u0432\u0440\u0435\u043c\u0435\u043d\u0438\",\"isSupermarket\":false}},\"number\":325,\"timestamp\":\"2020-03-24 12:58:30 +0300\",\"uuid\":\"85cb888b-8310-4ab9-ac1a-87d9bb4e0ec8\",\"version\":\"2\",\"widget\":{\"type\":\"cart\",\"name\":\"cart.controls\",\"id\":206862,\"revision_id\":139019,\"config_revision_id\":0,\"index\":26}},{\"action_type\":\"remove\",\"composer\":{\"slice\":{},\"cell\":{\"type\":\"product\",\"deliveryType\":\"FBO\",\"sellerId\":782,\"quantity\":1,\"originalPrice\":339,\"finalPrice\":264,\"index\":5,\"stock\":1,\"storehouseId\":660,\"categoryId\":40033,\"id\":159905756,\"title\":\"\u041c\u0435\u0445\u0430\u043d\u0438\u0447\u0435\u0441\u043a\u043e\u0435 \u0441\u0435\u0440\u0434\u0446\u0435. \u041a\u043b\u044e\u0447 \u043a \u0442\u0430\u0439\u043d\u0430\u043c \u043f\u0440\u043e\u0448\u043b\u043e\u0433\u043e. \u041a\u043d\u0438\u0433\u0430 1.\",\"isSupermarket\":false}},\"number\":326,\"timestamp\":\"2020-03-24 12:58:30 +0300\",\"uuid\":\"4f8669c8-a858-4542-8676-6d7dc1b902eb\",\"version\":\"2\",\"widget\":{\"type\":\"cart\",\"name\":\"cart.controls\",\"id\":206862,\"revision_id\":139019,\"config_revision_id\":0,\"index\":26}},{\"action_type\":\"remove\",\"composer\":{\"slice\":{},\"cell\":{\"type\":\"product\",\"deliveryType\":\"FBO\",\"sellerId\":782,\"quantity\":1,\"originalPrice\":294,\"finalPrice\":229,\"index\":5,\"stock\":1,\"storehouseId\":660,\"categoryId\":40040,\"id\":154075917,\"title\":\"\u041f\u0430\u043d\u0434\u0435\u043c\u043e\u043d\u0438\u0443\u043c. \u0413\u043e\u0440\u043e\u0434 \u0442\u0435\u043c\u043d\u044b\u0445 \u0441\u0435\u043a\u0440\u0435\u0442\u043e\u0432. \u041a\u043d\u0438\u0433\u0430 1.\",\"isSupermarket\":false}},\"number\":327,\"timestamp\":\"2020-03-24 12:58:30 +0300\",\"uuid\":\"36617829-478c-47db-8029-c732496f1f82\",\"version\":\"2\",\"widget\":{\"type\":\"cart\",\"name\":\"cart.controls\",\"id\":206862,\"revision_id\":139019,\"config_revision_id\":0,\"index\":26}},{\"action_type\":\"remove\",\"composer\":{\"slice\":{},\"cell\":{\"type\":\"product\",\"deliveryType\":\"FBO\",\"sellerId\":782,\"quantity\":1,\"originalPrice\":491,\"finalPrice\":383,\"index\":5,\"stock\":1,\"storehouseId\":660,\"categoryId\":40040,\"id\":148803704,\"title\":\"\u042d\u0440\u0430\u0433\u043e\u043d. \u041a\u043d\u0438\u0433\u0430 1. | \u041f\u0430\u043e\u043b\u0438\u043d\u0438 \u041a\u0440\u0438\u0441\u0442\u043e\u0444\u0435\u0440\",\"isSupermarket\":false}},\"number\":328,\"timestamp\":\"2020-03-24 12:58:30 +0300\",\"uuid\":\"53a23e7e-cf7c-4a53-bf50-cfcbc98289aa\",\"version\":\"2\",\"widget\":{\"type\":\"cart\",\"name\":\"cart.controls\",\"id\":206862,\"revision_id\":139019,\"config_revision_id\":0,\"index\":26}},{\"action_type\":\"remove\",\"composer\":{\"slice\":{},\"cell\":{\"type\":\"product\",\"deliveryType\":\"FBO\",\"sellerId\":782,\"quantity\":1,\"originalPrice\":409,\"finalPrice\":319,\"index\":5,\"stock\":1,\"storehouseId\":660,\"categoryId\":40040,\"id\":150363956,\"title\":\"\u0411\u043e\u043b\u043e\u0442\u043d\u0438\u0446\u0430\",\"isSupermarket\":false}},\"number\":329,\"timestamp\":\"2020-03-24 12:58:30 +0300\",\"uuid\":\"61a4b6ac-7225-426c-83fe-3eb687fbb39f\",\"version\":\"2\",\"widget\":{\"type\":\"cart\",\"name\":\"cart.controls\",\"id\":206862,\"revision_id\":139019,\"config_revision_id\":0,\"index\":26}},{\"action_type\":\"remove\",\"composer\":{\"slice\":{},\"cell\":{\"type\":\"product\",\"deliveryType\":\"FBO\",\"sellerId\":782,\"quantity\":1,\"originalPrice\":449,\"finalPrice\":350,\"index\":5,\"stock\":1,\"storehouseId\":660,\"categoryId\":40042,\"id\":161109552,\"title\":\"\u0421\u0430\u0431\u0440\u0438\u043d\u0430. \u041b\u0435\u0434\u0435\u043d\u044f\u0449\u0438\u0435 \u0434\u0443\u0448\u0443 \u043f\u0440\u0438\u043a\u043b\u044e\u0447\u0435\u043d\u0438\u044f. \u0421\u0435\u0437\u043e\u043d \u0432\u0435\u0434\u044c\u043c\u044b, 1.\",\"isSupermarket\":false}},\"number\":330,\"timestamp\":\"2020-03-24 12:58:30 +0300\",\"uuid\":\"0a3160e4-70af-4987-b9ef-51a5263e325d\",\"version\":\"2\",\"widget\":{\"type\":\"cart\",\"name\":\"cart.controls\",\"id\":206862,\"revision_id\":139019,\"config_revision_id\":0,\"index\":26}},{\"action_type\":\"remove\",\"composer\":{\"slice\":{},\"cell\":{\"type\":\"product\",\"deliveryType\":\"FBO\",\"sellerId\":782,\"quantity\":1,\"originalPrice\":454,\"finalPrice\":454,\"index\":5,\"stock\":1,\"storehouseId\":660,\"categoryId\":40040,\"id\":148803721,\"title\":\"\u0427\u0430\u0441\u043e\u0434\u0435\u0438. \u0427\u0430\u0441\u043e\u0432\u043e\u0439 \u043a\u043b\u044e\u0447. \u041a\u043d\u0438\u0433\u0430 1. | \u0429\u0435\u0440\u0431\u0430 \u041d\u0430\u0442\u0430\u043b\u044c\u044f \u0412\u0430\u0441\u0438\u043b\u044c\u0435\u0432\u043d\u0430\",\"isSupermarket\":false}},\"number\":331,\"timestamp\":\"2020-03-24 12:58:30 +0300\",\"uuid\":\"5b7a1402-3754-4429-86f6-da58ca7ab2ad\",\"version\":\"2\",\"widget\":{\"type\":\"cart\",\"name\":\"cart.controls\",\"id\":206862,\"revision_id\":139019,\"config_revision_id\":0,\"index\":26}}]}\n", "webapp_id": "56d69c95-2cc0-4da5-92e3-b514f3681932", "src_port": 44332, "raw_uri": "https://www.ozon.ru/api/tracker.bx/v2/composer_events", "obj_id": "0c6c5546-be5a-4523-b089-080aa771ce7b", "uri": {"username": "", "password": "", "fragment": "", "hostname": "www.ozon.ru", "path": "/api/tracker.bx/v2/composer_events", "query": "", "scheme": "https", "port": -1}, "method": "POST", "src_ip": "10.0.0.14", "headers": [[":method", "POST"], [":authority", "www.ozon.ru"], [":scheme", "https"], [":path", "/api/tracker.bx/v2/composer_events"], ["content-length", "12373"], ["sec-fetch-dest", "empty"], ["user-agent", "Mozilla/5.0 (X11; Linux x86_64) AppleWebKit/537.36 (KHTML, like Gecko) Chrome/80.0.3987.0 Safari/537.36"], ["content-type", "text/plain;charset=UTF-8"], ["accept", "*/*"], ["origin", "https://www.ozon.ru"], ["sec-fetch-site", "same-origin"], ["sec-fetch-mode", "no-cors"], ["referer", "https://www.ozon.ru/cart"], ["accept-encoding", "gzip, deflate, br"], ["accept-language", "ru-RU,ru;q=0.9,en-US;q=0.8,en;q=0.7"], ["cookie", "access_token=1ZZMB0zWIaJydHsqCwN02a2rPMk; refresh_token=aeXj1KfbONiIQ-IFfjmpJKZ4l-lOIk96SlbpNWd56rzLZ_mJnPO55Rda1FXwlIl8gU7LXSkx9WKcDWR_JoiDc5xxZ1H8m7Z82aW_Yvr2uOrJZKhua3bpAQJuwbVQWXz1d08d8MaVfIJ18TvqI4nCUio-9vnCcp-Ce6_Fx3D2oaL86QIMQp0PLK37E5r9ajh7HfEMBcmntcBVU4UcxEEBI3UpRndHfFi-mgGepLp4KQI1pf_4kIQHDspOsNVvZ9HX_4U63XjiKdMGLh6H5JmSUHX0ArKg05fN-CTkrE9S6yhqxdrgl0s6uMToaCXecTeUBcczn6-6SA7FjWvVxIcq0-iYfGS1Why2y76achqlZIPz40mJ_65cGA2-xSaVkaOqwK8HOx50jyWDUuHPQZY6sdLj57x95CYRnx9nXbaV95xZZebPyrsUsh1nBQrXmepg; token_expiration=\"2020-03-24T14:27:03.7628265+03:00\"; abGroup=24; SessionID=g7f8O9KUQK+7aw6nLff3Qw; xcid=53ebd41441e6049b016281d59dc38ea7; visid_incap_1101384=tE5mKj+LRGibizJ8fNkwtWfSeV4AAAAAQUIPAAAAAABXjldPTfncrQ7+EodZDOKH; nlbi_1101384=hNVDIz1Y3hGp3CglB/dZHAAAAACfdedmByGk2T9R8F0EJMED; incap_ses_585_1101384=drt2f9xGi05GS53A31ceCGfSeV4AAAAADsuTWOS/rRPx5nc9VZBJxQ==; _gcl_au=1.1.1798603991.1585042037; _ga=GA1.2.1657344491.1585042046; _gid=GA1.2.386063420.1585042046; __exponea_etc__=af76b70c-6db1-11ea-a7ab-dabc1de6bbbf; __exponea_time2__=-0.12854528427124023; _fbp=fb.1.1585042051554.680872615; tmr_lvid=b0bbf834e2844ec2ce399491a774cbf6; tmr_lvidTS=1585042053003; flocktory-uuid=4bc91c0e-50c0-46a6-abbf-b70e9257a2fd-0; __sonar=8858484612482995221; o_cdm=1585042070166; userId=0; ap_visited=true; tmr_detect=0%7C1585043836878; _dc_gtm_UA-37420525-1=1; _gat_UA-37420525-1=1; tmr_reqNum=448"]], "dst_port": 80, "protocol": 1.1, "dst_ip": "10.72.55.226"}