{"body": "{\"operationName\":\"getHomepage\",\"variables\":{},\"query\":\"query getHomepage {\\n  homepage {\\n    rows {\\n      __typename\\n      correlationName\\n      ... on JobCardRow {\\n        title\\n        subTitle\\n        solMetadata\\n        jobCount\\n        searchCriteria {\\n          keyword\\n          locations {\\n            id\\n            name\\n            __typename\\n          }\\n          categories {\\n            id\\n            name\\n            __typename\\n          }\\n          __typename\\n        }\\n        items {\\n          solMetadata\\n          id\\n          title\\n          company {\\n            name\\n            __typename\\n          }\\n          logo {\\n            url\\n            __typename\\n          }\\n          postedDate\\n          locations {\\n            name\\n            __typename\\n          }\\n          isNew\\n          isStandout\\n          isSaved\\n          savedJobId\\n          url\\n          __typename\\n        }\\n        __typename\\n      }\\n      ... on SearchCardRow {\\n        title\\n        subTitle\\n        items {\\n          newJobCount\\n          criteria {\\n            keyword\\n            locations {\\n              id\\n              name\\n              __typename\\n            }\\n            categories {\\n              id\\n              name\\n              __typename\\n            }\\n            __typename\\n          }\\n          __typename\\n        }\\n        __typename\\n      }\\n    }\\n    __typename\\n  }\\n}\\n\"}\n", "webapp_id": "56d69c95-2cc0-4da5-92e3-b514f3681932", "src_port": 44332, "raw_uri": "https://xapi-homepage-prod.supercharge-srp.co/graphql?country=hk", "obj_id": "96a57448-d1c3-4413-81b1-5fc53c5b8c18", "uri": {"username": "", "password": "", "fragment": "", "hostname": "xapi-homepage-prod.supercharge-srp.co", "path": "/graphql", "query": "country=hk", "scheme": "https", "port": -1}, "method": "POST", "src_ip": "10.0.0.14", "headers": [["accept", "*/*"], ["solvisitorid", "e6badf2b-8a18-42ad-8f12-7f88853d8014"], ["referer", "https://hk.jobsdb.com/hk"], ["sec-fetch-dest", "empty"], ["user-agent", "Mozilla/5.0 (X11; Linux x86_64) AppleWebKit/537.36 (KHTML, like Gecko) Chrome/80.0.3987.0 Safari/537.36"], ["s_vi", "[CS]v1|2F35A8FE851585B5-40000BA5443436B5[CE]"], ["content-type", "application/json"]], "dst_port": 80, "protocol": 1.1, "dst_ip": "10.72.55.226"}