{"body": "{\"operationName\":\"prices\",\"variables\":{\"productIds\":[\"30043140\",\"30048681\",\"30048680\",\"30048682\",\"30043141\",\"30042966\",\"30038415\",\"30040133\",\"30042965\",\"30042960\",\"30042962\",\"30043143\"],\"regionId\":\"1\"},\"query\":\"query prices($productIds: [String]!, $regionId: String!) {\\n  prices(productIds: $productIds, regionId: $regionId) {\\n    productId\\n    actionPrice\\n    basePrice\\n    economy\\n    bonusRubles\\n    __typename\\n  }\\n}\\n\"}\n", "webapp_id": "56d69c95-2cc0-4da5-92e3-b514f3681932", "src_port": 44332, "raw_uri": "https://www.mvideo.ru/.rest/graphql", "obj_id": "1ce5f4f2-ebd0-4572-84e7-345da5a1c5bb", "uri": {"username": "", "password": "", "fragment": "", "hostname": "www.mvideo.ru", "path": "/.rest/graphql", "query": "", "scheme": "https", "port": -1}, "method": "POST", "src_ip": "10.0.0.14", "headers": [["accept", "*/*"], ["referer", "https://www.mvideo.ru/gadzhety-64/chasy-detskie-5547/f/category=chasy-s-gps-trekerom-5548"], ["sec-fetch-dest", "empty"], ["adrum", "isAjax:true"], ["user-agent", "Mozilla/5.0 (X11; Linux x86_64) AppleWebKit/537.36 (KHTML, like Gecko) Chrome/80.0.3987.0 Safari/537.36"], ["content-type", "application/json"]], "dst_port": 80, "protocol": 1.1, "dst_ip": "10.72.55.226"}