{"body": "{\"operationName\":\"trackViews\",\"variables\":{\"decisionIds\":[\"101031322436242738\",\"102366438955333811\",\"101184267495135034\",\"102254468380156007\",\"101751674608710853\",\"101999341998382826\"]},\"query\":\"mutation trackViews($decisionIds: [ID!]!) {\\n  trackViews(decisionIds: $decisionIds)\\n}\\n\"}\n", "webapp_id": "56d69c95-2cc0-4da5-92e3-b514f3681932", "src_port": 44332, "raw_uri": "https://graphql.stackshare.io/graphql", "obj_id": "84dd0979-31d8-47de-8c14-5cbc4b1a7728", "uri": {"username": "", "password": "", "fragment": "", "hostname": "graphql.stackshare.io", "path": "/graphql", "query": "", "scheme": "https", "port": -1}, "method": "POST", "src_ip": "10.0.0.14", "headers": [["accept", "*/*"], ["referer", "https://stackshare.io/apache-httpd"], ["sec-fetch-dest", "empty"], ["x-csrf-token", "ipb8i/2oYJ2YFJU+vX94nbW0jEEDy9e1/ZN3FUjxwpz6ktjGB4H5+AGVw7RUhnUAfUEP81NSySBo5A0fbHx6BA=="], ["user-agent", "Mozilla/5.0 (X11; Linux x86_64) AppleWebKit/537.36 (KHTML, like Gecko) Chrome/80.0.3987.0 Safari/537.36"], ["content-type", "application/json"]], "dst_port": 80, "protocol": 1.1, "dst_ip": "10.72.55.226"}